dxql/__init__.py
dxql/grammar.lark
dxql/search.py
tests/__init__.py
tests/test_search.py
dxql-0.0.6.dist-info/LICENSE
dxql-0.0.6.dist-info/METADATA
dxql-0.0.6.dist-info/WHEEL
dxql-0.0.6.dist-info/top_level.txt
dxql-0.0.6.dist-info/RECORD
