Metadata-Version: 2.1
Name: dxql
Version: 0.0.6
Summary: Data eXploration Query Language (DXQL)
Home-page: https://github.com/Frechetta/DXQL
Author: Eric Frechette
Author-email: frechetta93@gmail.com
License: UNKNOWN
Keywords: data search query language
Platform: UNKNOWN
Classifier: Programming Language :: Python
Classifier: Intended Audience :: Developers
Requires-Python: >= 3.7
Requires-Dist: lark-parser (==0.7.1)
Provides-Extra: test
Requires-Dist: pytest (>=5.0.1) ; extra == 'test'
Requires-Dist: pytest-cov (>=2.7.1) ; extra == 'test'
Requires-Dist: codecov (>=2.0.15) ; extra == 'test'
